ChangeLog
MANIFEST.in
README.md
README.txt
migrations.py
requirements.txt
setup.py
remindme/Remindme.py
remindme/Repository.py
remindme/__init__.py
remindme/cli.py
remindme/config.py
remindme/metadata.py
remindme/utils.py
remindme.egg-info/PKG-INFO
remindme.egg-info/SOURCES.txt
remindme.egg-info/dependency_links.txt
remindme.egg-info/entry_points.txt
remindme.egg-info/requires.txt
remindme.egg-info/top_level.txt
test/test_Remindme.py
test/test_RemindmeRepository.py
test/test_cli.py
test/test_migrations.py
test/test_utils.py