Metadata-Version: 1.1
Name: remindme
Version: 0.8.0
Summary: Command Line Application for reminding you of something
Home-page: https://github.com/GochoMugo/remindme
Author: Gocho Mugo I
Author-email: mugo@forfuture.co.ke
License: MIT
Download-URL: https://github.com/GochoMugo/remindme/zipball/master
Keywords: remindme,remind,remember,cli
Platform: UNKNOWN
Classifier: Development Status :: 5 - Production/Stable
Classifier: Environment :: Console
Classifier: Intended Audience :: End Users/Desktop
Classifier: License :: OSI Approved
Classifier: License :: OSI Approved :: MIT License
Classifier: Natural Language :: English
Classifier: Operating System :: OS Independent
Classifier: Programming Language :: Python
Classifier: Programming Language :: Python :: 2
Classifier: Programming Language :: Python :: 2.7
Classifier: Programming Language :: Python :: 3
Classifier: Programming Language :: Python :: 3.3
Classifier: Programming Language :: Python :: 3.4
